odoo9_addon_hr_timesheet_sheet_restrict_analytic-9.0.1.0.0-py2.7-nspkg.pth
odoo9_addon_hr_timesheet_sheet_restrict_analytic-9.0.1.0.0.dist-info/DESCRIPTION.rst
odoo9_addon_hr_timesheet_sheet_restrict_analytic-9.0.1.0.0.dist-info/METADATA
odoo9_addon_hr_timesheet_sheet_restrict_analytic-9.0.1.0.0.dist-info/RECORD
odoo9_addon_hr_timesheet_sheet_restrict_analytic-9.0.1.0.0.dist-info/WHEEL
odoo9_addon_hr_timesheet_sheet_restrict_analytic-9.0.1.0.0.dist-info/metadata.json
odoo9_addon_hr_timesheet_sheet_restrict_analytic-9.0.1.0.0.dist-info/namespace_packages.txt
odoo9_addon_hr_timesheet_sheet_restrict_analytic-9.0.1.0.0.dist-info/top_level.txt
odoo_addons/hr_timesheet_sheet_restrict_analytic/README.rst
odoo_addons/hr_timesheet_sheet_restrict_analytic/__init__.py
odoo_addons/hr_timesheet_sheet_restrict_analytic/__openerp__.py
odoo_addons/hr_timesheet_sheet_restrict_analytic/models/__init__.py
odoo_addons/hr_timesheet_sheet_restrict_analytic/models/account_analytic_account.py
odoo_addons/hr_timesheet_sheet_restrict_analytic/models/account_analytic_line.py
odoo_addons/hr_timesheet_sheet_restrict_analytic/static/description/icon.png
odoo_addons/hr_timesheet_sheet_restrict_analytic/static/src/js/restrict_timesheet.js
odoo_addons/hr_timesheet_sheet_restrict_analytic/views/analytic_view.xml
odoo_addons/hr_timesheet_sheet_restrict_analytic/views/hr_timesheet_restrict_analytic.xml
odoo_addons/hr_timesheet_sheet_restrict_analytic/views/hr_timesheet_sheet_view.xml
